{
  "id": "ryc-016",
  "collectionNumber": "RC-016",
  "title": "Star Wars - The Empire Strikes Back",
  "price": 350000,
  "category": "Komik Star Wars",
  "condition": "Good",
  "badge": "Limited",
  "status": "Available",
  "description": "Adaptasi resmi Star Wars Episode V: The Empire Strikes Back terbitan Gramedia tahun 1997 dalam Bahasa Indonesia. Dilengkapi ilustrasi karya Tim & Greg Hildebrandt, edisi ini menjadi salah satu collectible yang semakin sulit ditemukan oleh kolektor Star Wars dan komik pop culture.",
  "featured": false,
  "tags": [
    "Star Wars",
    "Gramedia",
    "Sci-Fi",
    "Original"
  ]
}