{
  "id": "ryc-026",
  "collectionNumber": "RC-026",
  "title": "'82 Toyota Supra",
  "price": 73000,
  "category": "Hot Wheels",
  "condition": "Mint",
  "badge": "Limited",
  "status": "Available",
  "description": "Hot Wheels '82 Toyota Supra dari seri J-Imports yang menghadirkan salah satu ikon JDM legendaris dengan balutan warna silver dan livery klasik khas era 1980-an. Masih dalam kondisi blister dan card yang terawat sehingga cocok untuk koleksi, display, maupun investasi diecast.",
  "featured": false,
  "tags": [
    "Hot Wheels",
    "Toyota Supra",
    "J-Imports",
    "Original"
  ]
}